domsync/__init__.py
domsync/components.py
domsync/core.py
domsync/domsync_server.py
domsync/version.py
domsync-0.1.2.dist-info/LICENSE
domsync-0.1.2.dist-info/METADATA
domsync-0.1.2.dist-info/WHEEL
domsync-0.1.2.dist-info/top_level.txt
domsync-0.1.2.dist-info/RECORD
