Metadata-Version: 2.1
Name: domsync
Version: 0.1.2
Summary: Python server-side DOM synchronised with Browser
Home-page: https://github.com/pdivos/domsync
Author: pdivos
Author-email: Peter Divos <pdivos@gmail.com>
License: BSD
Project-URL: Documentation, https://domsync.readthedocs.io/
License-File: LICENSE
Requires-Dist: websockets
